MANIFEST.in
README.md
setup.py
FGPIO/RFtest.py
FGPIO/SCT013_v_io.py
FGPIO/UltraSonic_io.py
FGPIO/__init__.py
FGPIO/bt_io.py
FGPIO/buzz_io.py
FGPIO/device_io.py
FGPIO/dht11_io.py
FGPIO/f_menu.py
FGPIO/f_spi.py
FGPIO/f_thread.py
FGPIO/font_io.py
FGPIO/gaz_sensor_io.py
FGPIO/hrlv_max_sonar_io.py
FGPIO/i2c_device_io.py
FGPIO/i2c_ext_io.py
FGPIO/i2c_io.py
FGPIO/lcd_12864.py
FGPIO/lcd_12864_hspi.py
FGPIO/lcd_i2c_io.py
FGPIO/lcd_io.py
FGPIO/lcd_lpt_io.py
FGPIO/led_io.py
FGPIO/lum_capteur_io.py
FGPIO/max7219_io.py
FGPIO/mcp23017_io.py
FGPIO/mcp300x_hspi_io.py
FGPIO/mcp300x_io.py
FGPIO/mpu_6050_io.py
FGPIO/nrf24l01_io.py
FGPIO/on_off_output_device_io.py
FGPIO/pca9555_io.py
FGPIO/pin_ext_io.py
FGPIO/pin_io.py
FGPIO/prise.py
FGPIO/qrd1114_io.py
FGPIO/rain_sensor_io.py
FGPIO/rcSwitch_io.py
FGPIO/relay_io.py
FGPIO/rf_recept_io.py
FGPIO/rotary_encoder_io.py
FGPIO/rpiduino_io.py
FGPIO/sen0018_io.py
FGPIO/servo_motor_io.py
FGPIO/test_dht11.py
FGPIO/test_gyro.py
FGPIO/test_servo.py
FGPIO.egg-info/PKG-INFO
FGPIO.egg-info/SOURCES.txt
FGPIO.egg-info/dependency_links.txt
FGPIO.egg-info/top_level.txt