Metadata-Version: 1.1
Name: FGPIO
Version: 0.6.1
Summary: A package for managing E/S of Raspberry pi or PCduino. Gestion des E/S d'un Raspberry PI ou d'un pcduino
Home-page: UNKNOWN
Author: FredThx
Author-email: FredThx@gmail.com
License: WTFPL
Platform: UNKNOWN
Classifier: Programming Language :: Python
Classifier: Development Status :: 4 - Beta
Classifier: License :: OSI Approved
Classifier: Natural Language :: French
Classifier: Operating System :: OS Independent
Classifier: Programming Language :: Python :: 2.7
